[
  {
    "hanzi": "函数 *y = √(x + 2)* 的反函数是 ( )",
    "options": [
      "y = x² - 2, x ≥ 0",
      "y = x² - 2, x ≥ -2",
      "y = x² + 2, x ≥ 0",
      "y = x² + 2, x ≥ -2"
    ],
    "answer": 0
  },
  {
    "hanzi": "不等式 *2x² - 5x - 3 < 0* 的解集是 ( )",
    "options": [
      "(-1/2, 3)",
      "(-3, 1/2)",
      "(-∞, -1/2) ∪ (3, +∞)",
      "(-∞, -3) ∪ (1/2, +∞)"
    ],
    "answer": 0
  },
  {
    "hanzi": "若 a < b < 0，下列哪一项是正确的? ( )",
    "options": [
      "a² < b²",
      "|a| < |b|",
      "a³ < b³",
      "1/a < 1/b"
    ],
    "answer": 0
  },
  {
    "hanzi": "不等式 *|2x - 3| ≤ 1* 的解集是 ( )",
    "options": [
      "[1, 2]",
      "(1, 2)",
      "(-∞, 1] ∪ [2, +∞)",
      "(-∞, 1) ∪ (2, +∞)"
    ],
    "answer": 0
  },
  {
    "hanzi": "设 *i* 为虚数单位，复数 z = i² + i³，则 *z* = ( )",
    "options": [
      "-1 - i",
      "-1 + i",
      "1 - i",
      "1 + i"
    ],
    "answer": 0
  },
  {
    "hanzi": "不等式 *(1/3)^(x²) ≤ 1/27* 的解集是 ( )",
    "options": [
      "(-∞, -√3] ∪ [√3, +∞)",
      "[-√3, √3]",
      "(-∞, -3] ∪ [3, +∞)",
      "[-3, 3]"
    ],
    "answer": 0
  },
  {
    "hanzi": "函数 *y = 1 / (x² - 4)* 的定义域是 ( )",
    "options": [
      "(-2, 2)",
      "[-2, 2]",
      "(-∞, -2) ∪ (2, +∞)",
      "(-∞, -2] ∪ [2, +∞)"
    ],
    "answer": 0
  },
  {
    "hanzi": "不等式 *log₅ (2x + 3) > 1* 的解集是 ( )",
    "options": [
      "(-3/2, 1)",
      "(1, +∞)",
      "(-∞, 1)",
      "(-3/2, +∞)"
    ],
    "answer": 0
  },
  {
    "hanzi": "已知函数 *f(x) = x⁴ - 8x² + 2*，则 f(x) 在区间 [-3, 3] 上的最小值是 ( )",
    "options": [
      "-14",
      "-12",
      "-10",
      "-8"
    ],
    "answer": 0
  },
  {
    "hanzi": "若关于 *x* 的方程 *x² + 2x + m = 0* 有两个不相等的实数根，则实数 *m* 的取值范围是 ( )",
    "options": [
      "m < 1",
      "m > 1",
      "m < -1",
      "m > -1"
    ],
    "answer": 0
  },
  {
    "hanzi": "等差数列 {aₙ} 中，*a₁ + a₆ = 12*，*a₄ = 7*，则 a₁₀ = ( )",
    "options": [
      "15",
      "16",
      "17",
      "18"
    ],
    "answer": 0
  },
  {
    "hanzi": "过点 (2, -3) 且与直线 *x - 2y + 4 = 0* 平行的直线方程是 ( )",
    "options": [
      "x - 2y - 8 = 0",
      "x - 2y + 8 = 0",
      "2x + y - 1 = 0",
      "x + 2y + 4 = 0"
    ],
    "answer": 0
  },
  {
    "hanzi": "若 *cos α = 2/3*，则 sin 2α 的最大可能值是 ( )",
    "options": [
      "4/9",
      "2√5/9",
      "4√5/9",
      "2/3"
    ],
    "answer": 0
  },
  {
    "hanzi": "点 *P(2, -1)* 关于直线 y = x 的对称点坐标是 ( )",
    "options": [
      "(-1, 2)",
      "(1, -2)",
      "(-2, 1)",
      "(2, 1)"
    ],
    "answer": 0
  },
  {
    "hanzi": "抛物线 *y² = 12x* 的准线方程是 ( )",
    "options": [
      "x = -3",
      "x = 3",
      "y = -3",
      "y = 3"
    ],
    "answer": 0
  },
  {
    "hanzi": "若 *sin α = -3/5* 且 α 在第三象限，则 *cos(α/2)* = ( )",
    "options": [
      "-√10/10",
      "-3√10/10",
      "√10/10",
      "3√10/10"
    ],
    "answer": 0
  },
  {
    "hanzi": "函数 *y = tan(2x)* 的定义域是 ( )",
    "options": [
      "{x | x ≠ kπ/2 + π/4, k ∈ Z}",
      "{x | x ≠ kπ + π/2, k ∈ Z}",
      "{x | x ≠ 2kπ + π/2, k ∈ Z}",
      "{x | x ≠ kπ/2, k ∈ Z}"
    ],
    "answer": 0
  },
  {
    "hanzi": "已知圆锥的底面半径为 3，高为 4，则该圆锥的侧面积是 ( )",
    "options": [
      "12π",
      "15π",
      "18π",
      "24π"
    ],
    "answer": 0
  },
  {
    "hanzi": "两平面 *x + y - 2z + 1 = 0* 和 *2x - y + z - 3 = 0* 的夹角是 ( )",
    "options": [
      "arccos(1/3)",
      "arccos(2/3)",
      "arccos(√6/6)",
      "arccos(√6/3)"
    ],
    "answer": 0
  },
  {
    "hanzi": "已知向量 *a = (3, 4)*，*b = (2, -1)*，则 *a* 与 *b* 的夹角的余弦值是 ( )",
    "options": [
      "2/25",
      "2/5",
      "√2/5",
      "2√2/5"
    ],
    "answer": 0
  },
  {
    "hanzi": "椭圆 *x²/16 + y²/7 = 1* 的焦点坐标是 ( )",
    "options": [
      "(±3, 0)",
      "(0, ±3)",
      "(±4, 0)",
      "(0, ±4)"
    ],
    "answer": 0
  },
  {
    "hanzi": "在△ABC中，角A、B、C的对边分别为a、b、c，且 *a = 3*, *b = 4*, *c = √13*，则角C = ( )",
    "options": [
      "30°",
      "45°",
      "60°",
      "90°"
    ],
    "answer": 0
  },
  {
    "hanzi": "圆 *x² + y² - 2x - 4y - 4 = 0* 上的点到直线 *3x + 4y - 5 = 0* 的最小距离是 ( )",
    "options": [
      "1",
      "2",
      "3",
      "4"
    ],
    "answer": 0
  },
  {
    "hanzi": "函数 *f(x) = 2 sin x + 3 cos x* 的最大值是 ( )",
    "options": [
      "√5",
      "√13",
      "5",
      "13"
    ],
    "answer": 0
  },
  {
    "hanzi": "极限 *lim_{x→3} (x² - 9)/(x - 3)* = ( )",
    "options": [
      "0",
      "3",
      "6",
      "Tidak ada"
    ],
    "answer": 0
  },
  {
    "hanzi": "函数 *f(x) = x³ - 6x² + 9x - 2* 的极大值是 ( )",
    "options": [
      "0",
      "1",
      "2",
      "3"
    ],
    "answer": 0
  },
  {
    "hanzi": "不定积分 *∫ (5x⁴ - 8x³ + 6x²) dx* = ( )",
    "options": [
      "x⁵ - 2x⁴ + 2x³ + C",
      "5x⁵ - 8x⁴ + 6x³ + C",
      "x⁵ - 2x⁴ + 6x³ + C",
      "20x³ - 24x² + 12x + C"
    ],
    "answer": 0
  },
  {
    "hanzi": "导数 *d/dx [cos(3x - 2)]* = ( )",
    "options": [
      "-3 sin(3x - 2)",
      "3 sin(3x - 2)",
      "-sin(3x - 2)",
      "sin(3x - 2)"
    ],
    "answer": 0
  },
  {
    "hanzi": "曲线 y = ln x 在点 (e, 1) 处的切线斜率是 ( )",
    "options": [
      "1/e",
      "e",
      "1",
      "0"
    ],
    "answer": 0
  },
  {
    "hanzi": "定积分 *∫₀^{π/4} sec² x dx* = ( )",
    "options": [
      "0",
      "1",
      "√2",
      "2"
    ],
    "answer": 0
  },
  {
    "hanzi": "函数 f(x) = cos x 的麦克劳林级数展开式中，x⁴ 项的系数是 ( )",
    "options": [
      "1/24",
      "-1/24",
      "1/6",
      "-1/6"
    ],
    "answer": 0
  },
  {
    "hanzi": "函数 *y = x⁴ - 4x³ + 4x²* 的单调递减区间是 ( )",
    "options": [
      "(-∞, 0)",
      "(0, 1)",
      "(1, 2)",
      "(-∞, 0) ∪ (1, 2)"
    ],
    "answer": 0
  },
  {
    "hanzi": "若 f(x) = arctan x，则 f'(1) = ( )",
    "options": [
      "1/4",
      "1/3",
      "1/2",
      "1"
    ],
    "answer": 0
  },
  {
    "hanzi": "极限 *lim_{x→0} (sin² x)/x²* = ( )",
    "options": [
      "0",
      "1",
      "2",
      "∞"
    ],
    "answer": 0
  },
  {
    "hanzi": "函数 *f(x) = x³ - 3x² + 2* 的极小值是 ( )",
    "options": [
      "-2",
      "0",
      "2",
      "4"
    ],
    "answer": 0
  },
  {
    "hanzi": "曲线 y = √x 与直线 y = x 所围成的图形的面积是 ( )",
    "options": [
      "1/6",
      "1/3",
      "1/2",
      "1"
    ],
    "answer": 0
  },
  {
    "hanzi": "袋中有 4 个红球，3 个白球。从中随机取 2 个球，则取到的两个球颜色相同的概率是 ( )",
    "options": [
      "2/7",
      "3/7",
      "4/7",
      "5/7"
    ],
    "answer": 0
  },
  {
    "hanzi": "已知 *P(A) = 0.7*, *P(B) = 0.6*，且 *P(A∩B) = 0.4*，则 P(A|B) = ( )",
    "options": [
      "2/3",
      "3/4",
      "4/7",
      "2/5"
    ],
    "answer": 0
  },
  {
    "hanzi": "一组数据的方差为 9，每个数据都减去 5，则新数据的方差是 ( )",
    "options": [
      "4",
      "9",
      "14",
      "81"
    ],
    "answer": 0
  },
  {
    "hanzi": "将 2 个不同的球随机放入 3 个不同的盒子中，则两个球在同一盒子的概率是 ( )",
    "options": [
      "1/9",
      "1/3",
      "2/3",
      "8/9"
    ],
    "answer": 0
  },
  {
    "hanzi": "复数 *z = (2 + i)(1 - 2i)*，则 *z* 的实部是 ( )",
    "options": [
      "0",
      "2",
      "4",
      "6"
    ],
    "answer": 0
  },
  {
    "hanzi": "数列 {aₙ} 的通项公式为 *aₙ = (-1)ⁿ · n*，则 a₁ + a₂ + a₃ + a₄ = ( )",
    "options": [
      "-2",
      "0",
      "2",
      "4"
    ],
    "answer": 0
  },
  {
    "hanzi": "直线 *3x - 4y - 10 = 0* 与圆 *x² + y² = 4* 的位置关系是 ( )",
    "options": [
      "Bersinggungan",
      "Berpotongan di dua titik",
      "Tidak berpotongan",
      "Garis melalui pusat lingkaran"
    ],
    "answer": 0
  },
  {
    "hanzi": "若 *log₄ (x + 3) = 2*，则 *x* = ( )",
    "options": [
      "5",
      "13",
      "16",
      "19"
    ],
    "answer": 0
  },
  {
    "hanzi": "等比数列 2, 6, 18, 54, ... 的第 6 项是 ( )",
    "options": [
      "162",
      "324",
      "486",
      "972"
    ],
    "answer": 0
  },
  {
    "hanzi": "方程 *x² + y² + 4x - 6y - 3 = 0* 所表示的圆的半径是 ( )",
    "options": [
      "2",
      "3",
      "4",
      "5"
    ],
    "answer": 0
  },
  {
    "hanzi": "函数 *f(x) = |x - 1|* 在 *x = 1* 处 ( )",
    "options": [
      "可导 (differentiable)",
      "连续但不可导 (continuous but not differentiable)",
      "不连续 (discontinuous)",
      "无法确定 (cannot be determined)"
    ],
    "answer": 0
  },
  {
    "hanzi": "若 *cos θ = -√3/2* 且 θ 在第二象限，则 θ = ( )",
    "options": [
      "30°",
      "150°",
      "210°",
      "330°"
    ],
    "answer": 0
  }
]